{
  "defaultView": "deck",
  "customTableRoot": "z_Assets/Tables",
  "customDeckRoot": "z_Assets/Decks",
  "disableDefaultWords": false,
  "deckJokers": false,
  "deckFlip": true,
  "deckTarot": true,
  "deckClipboard": false,
  "deckClipboardMode": "path",
  "diceClipboardMode": "code",
  "wordClipboardMode": "plain",
  "diceDeleteOnCopy": false,
  "inlineCounters": true,
  "inlineProgressMode": "clock",
  "inlineDynamicEdit": true,
  "standardOracleBias": false,
  "standardOracleEvents": false,
  "oracleLanguage": "en",
  "wordTab": "",
  "oracleTab": "default",
  "deckTab": "Business Card Dungeon",
  "mythicFactor": 5,
  "wordQuickValue": "",
  "wordQuickHeight": 100
}