{"path":".obsidian/plugins/text-extractor/cache/um/shared-content-dnd5e-bestiary-tome-of-blighted-horrors-tobh-umhjnbh2-iqx-png-b53ca514e5c083ddb63bd96cbe4d162e.json","text":"\"‘\\ Koo &b pe. T A . e E e Vj. A b a AN o P .,,,‘.;(,, A N g YN oy e TN S PR W Ly A A % iy R L B ,“.‘,:f%ig’ R % ok Y B e e SR 201 2l L’E‘g B e 0 DL B S é . AR 7\", 1P & 1 & o 1 \\-H - i@ 0y . . e § [ e vt LA e Ny ﬁ;?ir s A _r‘f e s o \\\\f\\g G A , - pololagr AR W S LR ‘ e i i e % i A i NN, e )/ o - A \" 1 i b oy 4 o e 1 o/ , b ] i \" w § e W ‘;, A g ‘gy AN § e i i S RN e PENE Y B Yl RN e o o) D e va o NN & el ol ) R G g ey F g R R L s T TN SRR L TS","libVersion":"0.0.0","langs":"eng","hash":"","size":0}